django_frontend_presets/__init__.py
django_frontend_presets/apps.py
django_frontend_presets/settings.py
django_frontend_presets/utils.py
django_frontend_presets/management/__init__.py
django_frontend_presets/management/commands/__init__.py
django_frontend_presets/management/commands/preset.py
django_frontend_presets/presets/Bootstrap.py
django_frontend_presets/presets/Init.py
django_frontend_presets/presets/Preset.py
django_frontend_presets/presets/React.py
django_frontend_presets/presets/Reset.py
django_frontend_presets/presets/Vue.py
django_frontend_presets/presets/__init__.py
django_frontend_presets/stubs/bootstrap/bootstrap.js
django_frontend_presets/stubs/init/webpack.mix.js
django_frontend_presets/stubs/init/resources/static/css/app.css
django_frontend_presets/stubs/init/resources/static/js/app.js
django_frontend_presets/stubs/init/resources/static/js/bootstrap.js
django_frontend_presets/stubs/init/resources/templates/base.html
django_frontend_presets/stubs/react/Example.js
django_frontend_presets/stubs/react/app.js
django_frontend_presets/stubs/react/webpack.mix.js
django_frontend_presets/stubs/vue/app.js
django_frontend_presets-0.1.2.dist-info/AUTHORS.rst
django_frontend_presets-0.1.2.dist-info/LICENSE
django_frontend_presets-0.1.2.dist-info/METADATA
django_frontend_presets-0.1.2.dist-info/WHEEL
django_frontend_presets-0.1.2.dist-info/top_level.txt
django_frontend_presets-0.1.2.dist-info/RECORD
