Metadata-Version: 2.1
Name: django-frontend-presets
Version: 0.1.2
Summary: Django frontend presets provide a command line that allow you to rapidly swap the front-end scaffolding for the application.
Home-page: https://github.com/mikemenard/django-frontend-presets
Author: Michael Menard
Author-email: hello@mikemenard.com
License: BSD
Keywords: django-frontend-presets
Platform: UNKNOWN
Classifier: Development Status :: 3 - Alpha
Classifier: Framework :: Django :: 1.11
Classifier: Intended Audience :: Developers
Classifier: License :: OSI Approved :: BSD License
Classifier: Natural Language :: English
Classifier: Programming Language :: Python :: 2
Classifier: Programming Language :: Python :: 2.7
Classifier: Programming Language :: Python :: 3
Classifier: Programming Language :: Python :: 3.5
Classifier: Programming Language :: Python :: 3.6
